simple_math_calijaaa/__init__.py
simple_math_calijaaa/dict_accessor.py
simple_math_calijaaa-0.3.3.dist-info/METADATA
simple_math_calijaaa-0.3.3.dist-info/WHEEL
simple_math_calijaaa-0.3.3.dist-info/licenses/LICENSE
simple_math_calijaaa-0.3.3.dist-info/RECORD
