Metadata-Version: 2.4
Name: simple-math-calijaaa
Version: 0.3.3
Summary: Библиотека с математическими алгоритмами и численными методами
Project-URL: Homepage, https://github.com/calijaaa/simple-math-calijaaa
Project-URL: Issues, https://github.com/calijaaa/simple-math-calijaaa/issues
Author-email: calijaaa <calijaaa@example.com>
License-File: LICENSE
Classifier: License :: OSI Approved :: MIT License
Classifier: Operating System :: OS Independent
Classifier: Programming Language :: Python :: 3
Requires-Python: >=3.8
